
{"items":[{"name":"VAMP","href":"VAMP.html","topicHref":"VAMP.html","topicUid":"VAMP","type":"Namespace","items":[{"name":"Core","href":"VAMP.Core.html","topicHref":"VAMP.Core.html","topicUid":"VAMP.Core","type":"Class"},{"name":"Extensions","href":"VAMP.Extensions.html","topicHref":"VAMP.Extensions.html","topicUid":"VAMP.Extensions","type":"Class"},{"name":"MyPluginInfo","href":"VAMP.MyPluginInfo.html","topicHref":"VAMP.MyPluginInfo.html","topicUid":"VAMP.MyPluginInfo","type":"Class"},{"name":"Plugin","href":"VAMP.Plugin.html","topicHref":"VAMP.Plugin.html","topicUid":"VAMP.Plugin","type":"Class"}]},{"name":"VAMP.Data","href":"VAMP.Data.html","topicHref":"VAMP.Data.html","topicUid":"VAMP.Data","type":"Namespace","items":[{"name":"Prefabs","href":"VAMP.Data.Prefabs.html","topicHref":"VAMP.Data.Prefabs.html","topicUid":"VAMP.Data.Prefabs","type":"Class"},{"name":"TerritoryAlignment","href":"VAMP.Data.TerritoryAlignment.html","topicHref":"VAMP.Data.TerritoryAlignment.html","topicUid":"VAMP.Data.TerritoryAlignment","type":"Enum"},{"name":"WorldRegions","href":"VAMP.Data.WorldRegions.html","topicHref":"VAMP.Data.WorldRegions.html","topicUid":"VAMP.Data.WorldRegions","type":"Class"}]},{"name":"VAMP.Models","href":"VAMP.Models.html","topicHref":"VAMP.Models.html","topicUid":"VAMP.Models","type":"Namespace","items":[{"name":"Player","href":"VAMP.Models.Player.html","topicHref":"VAMP.Models.Player.html","topicUid":"VAMP.Models.Player","type":"Class"}]},{"name":"VAMP.Patches","href":"VAMP.Patches.html","topicHref":"VAMP.Patches.html","topicUid":"VAMP.Patches","type":"Namespace","items":[{"name":"ChatMessagePatch","href":"VAMP.Patches.ChatMessagePatch.html","topicHref":"VAMP.Patches.ChatMessagePatch.html","topicUid":"VAMP.Patches.ChatMessagePatch","type":"Class"},{"name":"InitializationPatch","href":"VAMP.Patches.InitializationPatch.html","topicHref":"VAMP.Patches.InitializationPatch.html","topicUid":"VAMP.Patches.InitializationPatch","type":"Class"},{"name":"OnUserConnectedPatch","href":"VAMP.Patches.OnUserConnectedPatch.html","topicHref":"VAMP.Patches.OnUserConnectedPatch.html","topicUid":"VAMP.Patches.OnUserConnectedPatch","type":"Class"},{"name":"OnUserDisconnectedPatch","href":"VAMP.Patches.OnUserDisconnectedPatch.html","topicHref":"VAMP.Patches.OnUserDisconnectedPatch.html","topicUid":"VAMP.Patches.OnUserDisconnectedPatch","type":"Class"},{"name":"UnitSpawnerPatch","href":"VAMP.Patches.UnitSpawnerPatch.html","topicHref":"VAMP.Patches.UnitSpawnerPatch.html","topicUid":"VAMP.Patches.UnitSpawnerPatch","type":"Class"}]},{"name":"VAMP.Services","href":"VAMP.Services.html","topicHref":"VAMP.Services.html","topicUid":"VAMP.Services","type":"Namespace","items":[{"name":"CastleHeartService","href":"VAMP.Services.CastleHeartService.html","topicHref":"VAMP.Services.CastleHeartService.html","topicUid":"VAMP.Services.CastleHeartService","type":"Class"},{"name":"CastleTerritoryService","href":"VAMP.Services.CastleTerritoryService.html","topicHref":"VAMP.Services.CastleTerritoryService.html","topicUid":"VAMP.Services.CastleTerritoryService","type":"Class"},{"name":"EventScheduler","href":"VAMP.Services.EventScheduler.html","topicHref":"VAMP.Services.EventScheduler.html","topicUid":"VAMP.Services.EventScheduler","type":"Class"},{"name":"PlayerService","href":"VAMP.Services.PlayerService.html","topicHref":"VAMP.Services.PlayerService.html","topicUid":"VAMP.Services.PlayerService","type":"Class"},{"name":"SpawnService","href":"VAMP.Services.SpawnService.html","topicHref":"VAMP.Services.SpawnService.html","topicUid":"VAMP.Services.SpawnService","type":"Class"},{"name":"SystemService","href":"VAMP.Services.SystemService.html","topicHref":"VAMP.Services.SystemService.html","topicUid":"VAMP.Services.SystemService","type":"Class"}]},{"name":"VAMP.Structs","href":"VAMP.Structs.html","topicHref":"VAMP.Structs.html","topicUid":"VAMP.Structs","type":"Namespace","items":[{"name":"AngramBoss","href":"VAMP.Structs.AngramBoss.html","topicHref":"VAMP.Structs.AngramBoss.html","topicUid":"VAMP.Structs.AngramBoss","type":"Class"},{"name":"BaseTurret","href":"VAMP.Structs.BaseTurret.html","topicHref":"VAMP.Structs.BaseTurret.html","topicUid":"VAMP.Structs.BaseTurret","type":"Class"},{"name":"Boss","href":"VAMP.Structs.Boss.html","topicHref":"VAMP.Structs.Boss.html","topicUid":"VAMP.Structs.Boss","type":"Class"},{"name":"DyeableStructure","href":"VAMP.Structs.DyeableStructure.html","topicHref":"VAMP.Structs.DyeableStructure.html","topicUid":"VAMP.Structs.DyeableStructure","type":"Class"},{"name":"Event","href":"VAMP.Structs.Event.html","topicHref":"VAMP.Structs.Event.html","topicUid":"VAMP.Structs.Event","type":"Class"},{"name":"EventTrigger","href":"VAMP.Structs.EventTrigger.html","topicHref":"VAMP.Structs.EventTrigger.html","topicUid":"VAMP.Structs.EventTrigger","type":"Enum"},{"name":"HardBoss","href":"VAMP.Structs.HardBoss.html","topicHref":"VAMP.Structs.HardBoss.html","topicUid":"VAMP.Structs.HardBoss","type":"Class"},{"name":"HealingOrb","href":"VAMP.Structs.HealingOrb.html","topicHref":"VAMP.Structs.HealingOrb.html","topicUid":"VAMP.Structs.HealingOrb","type":"Class"},{"name":"Horse","href":"VAMP.Structs.Horse.html","topicHref":"VAMP.Structs.Horse.html","topicUid":"VAMP.Structs.Horse","type":"Class"},{"name":"PlayerData","href":"VAMP.Structs.PlayerData.html","topicHref":"VAMP.Structs.PlayerData.html","topicUid":"VAMP.Structs.PlayerData","type":"Struct"},{"name":"Turret","href":"VAMP.Structs.Turret.html","topicHref":"VAMP.Structs.Turret.html","topicUid":"VAMP.Structs.Turret","type":"Class"},{"name":"UltimateOrb","href":"VAMP.Structs.UltimateOrb.html","topicHref":"VAMP.Structs.UltimateOrb.html","topicUid":"VAMP.Structs.UltimateOrb","type":"Class"},{"name":"Unit","href":"VAMP.Structs.Unit.html","topicHref":"VAMP.Structs.Unit.html","topicUid":"VAMP.Structs.Unit","type":"Class"}]},{"name":"VAMP.Utilities","href":"VAMP.Utilities.html","topicHref":"VAMP.Utilities.html","topicUid":"VAMP.Utilities","type":"Namespace","items":[{"name":"BuffUtil","href":"VAMP.Utilities.BuffUtil.html","topicHref":"VAMP.Utilities.BuffUtil.html","topicUid":"VAMP.Utilities.BuffUtil","type":"Class"},{"name":"ChatUtil","href":"VAMP.Utilities.ChatUtil.html","topicHref":"VAMP.Utilities.ChatUtil.html","topicUid":"VAMP.Utilities.ChatUtil","type":"Class"},{"name":"DevUtil","href":"VAMP.Utilities.DevUtil.html","topicHref":"VAMP.Utilities.DevUtil.html","topicUid":"VAMP.Utilities.DevUtil","type":"Class"},{"name":"EntityUtil","href":"VAMP.Utilities.EntityUtil.html","topicHref":"VAMP.Utilities.EntityUtil.html","topicUid":"VAMP.Utilities.EntityUtil","type":"Class"},{"name":"ItemUtil","href":"VAMP.Utilities.ItemUtil.html","topicHref":"VAMP.Utilities.ItemUtil.html","topicUid":"VAMP.Utilities.ItemUtil","type":"Class"},{"name":"SettingsUtil","href":"VAMP.Utilities.SettingsUtil.html","topicHref":"VAMP.Utilities.SettingsUtil.html","topicUid":"VAMP.Utilities.SettingsUtil","type":"Class"},{"name":"UnitUtil","href":"VAMP.Utilities.UnitUtil.html","topicHref":"VAMP.Utilities.UnitUtil.html","topicUid":"VAMP.Utilities.UnitUtil","type":"Class"},{"name":"UnitUtil.SpawnedUnit","href":"VAMP.Utilities.UnitUtil.SpawnedUnit.html","topicHref":"VAMP.Utilities.UnitUtil.SpawnedUnit.html","topicUid":"VAMP.Utilities.UnitUtil.SpawnedUnit","type":"Class"}]}],"memberLayout":"SamePage","pdf":false}
